InputTools/InputTools.py
InputTools/__init__.py
InputTools/demo.py
Input_Tools-1.0.dist-info/LICENSE
Input_Tools-1.0.dist-info/METADATA
Input_Tools-1.0.dist-info/WHEEL
Input_Tools-1.0.dist-info/top_level.txt
Input_Tools-1.0.dist-info/RECORD
