Metadata-Version: 2.1
Name: Input-Tools
Version: 1.0
Summary: A Python Package to easily simulate input events
Home-page: https://github.com/Ahaan123/InputTools
Author: Ahaan Pandya
License: MIT
Platform: UNKNOWN
Requires-Dist: autopy
Requires-Dist: pynput
